{
  "schema": "calllint.evidence-manifest.v1",
  "subject": {
    "canonicalName": "mcp-registry/agency.lona-trading",
    "artifactDigest": "sha256:3ce01b0f8872a4aafa71b05210b2be91c3369714c5566bab9e57d1851ea58f0a"
  },
  "verdict": "REVIEW",
  "verdictLabel": "Review required",
  "completeness": "complete",
  "evidenceLevel": "E2",
  "evidenceRationale": "install config observed → static blast radius normalized into an authority inventory. Higher levels (E3 tool schema, E4 maintainer receipt, E5 sandbox) are not carried by a static page.",
  "status": {
    "verdict": "REVIEW",
    "completeness": "complete",
    "authorityClaimed": false,
    "reproducibility": {
      "pageDigest": "sha256:b0718630bf3957649f1dcbd36175caee7aa4580b1cdab7996409bd3d818e7859",
      "observedAt": "2026-07-17T00:00:00.000Z"
    },
    "evidenceLevel": "E2"
  },
  "authority": {
    "digest": "sha256:bab5bf331192afcca0f6a3a5800cda421baa72fb66a75676d3e78d1fd7b44497",
    "completeness": "complete",
    "capabilityCount": 1,
    "approvalRequired": [
      "external-network-access"
    ],
    "capabilities": [
      {
        "action": "connect",
        "resource": "network",
        "mutability": "mutating",
        "reversibility": "irreversible",
        "approvalRequirement": "review"
      }
    ]
  },
  "policyDigest": null,
  "reproducibility": {
    "pageDigest": "sha256:b0718630bf3957649f1dcbd36175caee7aa4580b1cdab7996409bd3d818e7859",
    "observedAt": "2026-07-17T00:00:00.000Z"
  },
  "engine": {
    "name": "calllint"
  },
  "correctionUrl": "https://github.com/calllint/calllint/issues/new?labels=trust-page-correction",
  "generatedAt": "2026-07-17T00:00:00.000Z",
  "signature": null
}
